{
    "3026": {
        "name": "Středočeský kraj",
        "data": {
            "women": [
                39996,
                41331,
                42409,
                32860,
                27392,
                34454,
                44027,
                50334,
                62142,
                60285,
                44781,
                41704,
                39189,
                44676,
                43112,
                29894,
                17689,
                11146,
                4572,
                870,
                59
            ],
            "men": [
                41813,
                43368,
                44454,
                35494,
                30177,
                36672,
                44939,
                50989,
                64951,
                65223,
                48307,
                43609,
                37841,
                40400,
                35539,
                21375,
                10461,
                5008,
                1662,
                243,
                16
            ]
        }
    },
    "3018": {
        "name": "Hlavní město Praha",
        "data": {
            "women": [
                34598,
                32122,
                30325,
                25090,
                33087,
                50658,
                55901,
                52689,
                55722,
                49976,
                37729,
                36925,
                32003,
                37962,
                38224,
                30700,
                16670,
                10949,
                5306,
                1251,
                96
            ],
            "men": [
                36237,
                33743,
                32344,
                25776,
                31670,
                49547,
                57768,
                55207,
                59049,
                52380,
                38071,
                35037,
                28801,
                30695,
                28182,
                20524,
                10209,
                5575,
                2272,
                340,
                22
            ]
        }
    },
    "3115": {
        "name": "Jihomoravský kraj",
        "data": {
            "women": [
                32641,
                30849,
                31101,
                25975,
                27095,
                35923,
                40257,
                41031,
                46892,
                46775,
                37039,
                36388,
                35280,
                39133,
                37754,
                28699,
                18122,
                11050,
                4942,
                1067,
                85
            ],
            "men": [
                34222,
                32413,
                32448,
                27270,
                28333,
                38173,
                43027,
                44762,
                50474,
                49280,
                38605,
                36843,
                33550,
                33961,
                29063,
                19708,
                10327,
                5095,
                1721,
                270,
                8
            ]
        }
    },
    "3140": {
        "name": "Moravskoslezský kraj",
        "data": {
            "women": [
                28599,
                28031,
                31128,
                27288,
                25456,
                30097,
                35031,
                35469,
                42656,
                46648,
                39596,
                40819,
                38292,
                41579,
                39788,
                29106,
                18291,
                9907,
                4072,
                845,
                52
            ],
            "men": [
                30347,
                29624,
                32395,
                28788,
                27096,
                32624,
                38004,
                38716,
                46038,
                48665,
                41194,
                41049,
                36080,
                35130,
                29632,
                18372,
                10498,
                4353,
                1285,
                192,
                9
            ]
        }
    },
    "3069": {
        "name": "Ústecký kraj",
        "data": {
            "women": [
                19586,
                19865,
                22566,
                19695,
                17830,
                20414,
                22788,
                24064,
                30171,
                33574,
                26305,
                25381,
                24053,
                28227,
                28650,
                17908,
                10761,
                5597,
                2194,
                474,
                30
            ],
            "men": [
                20243,
                21035,
                23664,
                20747,
                18819,
                22158,
                24694,
                25795,
                32237,
                35176,
                27188,
                25984,
                22680,
                24234,
                22607,
                12138,
                6042,
                2705,
                726,
                89,
                4
            ]
        }
    },
    "3034": {
        "name": "Jihočeský kraj",
        "data": {
            "women": [
                16302,
                15900,
                17188,
                14672,
                13521,
                16212,
                18544,
                19689,
                24228,
                25622,
                20732,
                20464,
                20390,
                22320,
                20931,
                14924,
                9384,
                5829,
                2294,
                447,
                42
            ],
            "men": [
                17008,
                17068,
                17792,
                15410,
                14520,
                17562,
                19848,
                20834,
                25641,
                26247,
                21204,
                20655,
                19970,
                20641,
                17735,
                10692,
                5535,
                2791,
                893,
                117,
                5
            ]
        }
    },
    "3123": {
        "name": "Olomoucký kraj",
        "data": {
            "women": [
                15911,
                15281,
                16854,
                14326,
                13675,
                16218,
                18216,
                19070,
                23618,
                25162,
                20164,
                20046,
                19868,
                22040,
                21314,
                15363,
                9898,
                5902,
                2442,
                492,
                33
            ],
            "men": [
                16515,
                16150,
                17453,
                14872,
                14360,
                17280,
                19766,
                20434,
                25619,
                26577,
                20622,
                20174,
                18839,
                19385,
                16558,
                10092,
                5615,
                2639,
                827,
                114,
                4
            ]
        }
    },
    "3042": {
        "name": "Plzeňský kraj",
        "data": {
            "women": [
                14688,
                14299,
                15531,
                12938,
                12834,
                15586,
                18059,
                19111,
                22642,
                23827,
                18442,
                18253,
                17697,
                20038,
                18944,
                13893,
                8388,
                5033,
                1973,
                362,
                19
            ],
            "men": [
                15394,
                14852,
                16230,
                13538,
                13482,
                17514,
                20074,
                20765,
                24385,
                25104,
                19647,
                18564,
                17034,
                18146,
                15684,
                9943,
                5224,
                2420,
                783,
                90,
                6
            ]
        }
    },
    "3131": {
        "name": "Zlínský kraj",
        "data": {
            "women": [
                14089,
                13628,
                14739,
                12955,
                11847,
                13891,
                15864,
                17108,
                21197,
                22813,
                18697,
                19313,
                18701,
                20476,
                19028,
                14204,
                9745,
                6023,
                2400,
                442,
                25
            ],
            "men": [
                14839,
                14376,
                15628,
                13712,
                12951,
                15095,
                17658,
                18898,
                22826,
                24218,
                19351,
                19221,
                18034,
                17606,
                14684,
                9279,
                5307,
                2568,
                784,
                105,
                6
            ]
        }
    },
    "3085": {
        "name": "Královéhradecký kraj",
        "data": {
            "women": [
                13320,
                13254,
                14638,
                12412,
                11672,
                13449,
                15049,
                16108,
                20138,
                21767,
                17482,
                17045,
                16524,
                19683,
                19486,
                13933,
                8472,
                5101,
                2278,
                452,
                23
            ],
            "men": [
                14089,
                13895,
                15481,
                13222,
                12860,
                15060,
                16519,
                17542,
                21671,
                23186,
                18194,
                17170,
                16130,
                17208,
                15400,
                9817,
                4989,
                2630,
                834,
                113,
                7
            ]
        }
    },
    "3093": {
        "name": "Pardubický kraj",
        "data": {
            "women": [
                13253,
                13132,
                13943,
                11742,
                11297,
                13270,
                14877,
                15751,
                19546,
                20617,
                16302,
                16070,
                15654,
                17975,
                16639,
                11993,
                7788,
                4951,
                1891,
                383,
                17
            ],
            "men": [
                14055,
                13755,
                14618,
                12653,
                12468,
                14834,
                16357,
                17143,
                21251,
                21950,
                16922,
                16041,
                15019,
                16005,
                13670,
                8431,
                4564,
                2324,
                789,
                89,
                8
            ]
        }
    },
    "3107": {
        "name": "Kraj Vysočina",
        "data": {
            "women": [
                12895,
                12511,
                13268,
                11736,
                10717,
                12593,
                14004,
                15041,
                18334,
                19784,
                16246,
                16375,
                15986,
                16952,
                16210,
                12171,
                8250,
                4867,
                1987,
                346,
                20
            ],
            "men": [
                13580,
                13069,
                13875,
                12372,
                11896,
                14011,
                15579,
                16549,
                19733,
                21021,
                16913,
                17020,
                16114,
                15766,
                13534,
                8446,
                4782,
                2326,
                709,
                66,
                7
            ]
        }
    },
    "3077": {
        "name": "Liberecký kraj",
        "data": {
            "women": [
                11332,
                11180,
                12341,
                10137,
                9381,
                11041,
                12959,
                13704,
                16862,
                18200,
                13998,
                13406,
                12747,
                15283,
                15828,
                9988,
                6026,
                3546,
                1504,
                314,
                23
            ],
            "men": [
                11850,
                11774,
                12854,
                10648,
                10276,
                12413,
                14066,
                14942,
                18446,
                19319,
                14586,
                13569,
                12031,
                13247,
                12614,
                7053,
                3506,
                1661,
                496,
                64,
                5
            ]
        }
    },
    "3051": {
        "name": "Karlovarský kraj",
        "data": {
            "women": [
                6533,
                6569,
                7712,
                6464,
                5920,
                6763,
                7932,
                8220,
                10483,
                11863,
                9674,
                9466,
                9258,
                10190,
                9992,
                6358,
                4384,
                2198,
                821,
                181,
                12
            ],
            "men": [
                6697,
                6950,
                8125,
                7044,
                6431,
                7656,
                8754,
                9124,
                10965,
                12357,
                10119,
                9800,
                8843,
                9123,
                7827,
                4364,
                2446,
                1117,
                329,
                35,
                4
            ]
        }
    }
}